ckanext/__init__.py
ckanext/iiif/__init__.py
ckanext/iiif/interfaces.py
ckanext/iiif/plugin.py
ckanext/iiif/builders/__init__.py
ckanext/iiif/builders/abc.py
ckanext/iiif/builders/manifest.py
ckanext/iiif/builders/utils.py
ckanext/iiif/logic/__init__.py
ckanext/iiif/logic/actions.py
ckanext/iiif/logic/auth.py
ckanext/iiif/routes/__init__.py
ckanext/iiif/routes/iiif.py
ckanext_iiif-4.0.1.dist-info/licenses/LICENSE
docs/_scripts/gen_api_pages.py
tests/integration/__init__.py
tests/integration/test_actions.py
tests/integration/test_auth.py
tests/integration/test_iiif_route.py
tests/unit/__init__.py
tests/unit/test_plugin.py
tests/unit/builders/__init__.py
tests/unit/builders/test_manifest.py
tests/unit/builders/test_utils.py
tests/unit/logic/__init__.py
tests/unit/logic/test_actions.py
tests/unit/logic/test_auth.py
tests/unit/routes/__init__.py
tests/unit/routes/test_iiif.py
ckanext_iiif-4.0.1.dist-info/METADATA
ckanext_iiif-4.0.1.dist-info/WHEEL
ckanext_iiif-4.0.1.dist-info/entry_points.txt
ckanext_iiif-4.0.1.dist-info/top_level.txt
ckanext_iiif-4.0.1.dist-info/RECORD
